ripgrepy/__init__.py
ripgrepy-1.0.1.dist-info/LICENSE
ripgrepy-1.0.1.dist-info/METADATA
ripgrepy-1.0.1.dist-info/WHEEL
ripgrepy-1.0.1.dist-info/top_level.txt
ripgrepy-1.0.1.dist-info/RECORD
