Metadata-Version: 2.1
Name: ripgrepy
Version: 1.0.1
Summary: UNKNOWN
Home-page: UNKNOWN
Author: Hapsida @securisec
License: UNKNOWN
Platform: UNKNOWN
Classifier: Programming Language :: Python :: 3.7
